hayai/__init__.py
hayai/decorator.py
hayai/loader.py
hayai-0.1.0.dist-info/METADATA
hayai-0.1.0.dist-info/WHEEL
hayai-0.1.0.dist-info/RECORD
